fusion_deploy/__init__.py
fusion_deploy/fusion_deploy.py
fusion_deploy-0.1.dist-info/LICENSE
fusion_deploy-0.1.dist-info/METADATA
fusion_deploy-0.1.dist-info/WHEEL
fusion_deploy-0.1.dist-info/entry_points.txt
fusion_deploy-0.1.dist-info/top_level.txt
fusion_deploy-0.1.dist-info/RECORD
